meta.py
ManHourCalendar-0.9.1b3.dist-info/DESCRIPTION.rst
ManHourCalendar-0.9.1b3.dist-info/METADATA
ManHourCalendar-0.9.1b3.dist-info/RECORD
ManHourCalendar-0.9.1b3.dist-info/WHEEL
ManHourCalendar-0.9.1b3.dist-info/entry_points.txt
ManHourCalendar-0.9.1b3.dist-info/metadata.json
ManHourCalendar-0.9.1b3.dist-info/top_level.txt
mhcalendar/__init__.py
mhcalendar/example.py
mhcalendar/io.py
mhcalendar/job.py
mhcalendar/log.py
mhcalendar/time_elements.py
scripts/__init__.py
scripts/mhcalendar.py
