Metadata-Version: 2.0
Name: ManHourCalendar
Version: 0.9.1b3
Summary: Calendar to manage your man-hour.
Home-page: https://github.com/wavky/ManHourCalendar
Author: Wavky Huang
Author-email: master@wavky.com
License: MIT
Keywords: man-hour,manhour,man hour,calendar,schedule
Platform: UNKNOWN
Classifier: Development Status :: 4 - Beta
Classifier: Intended Audience :: Developers
Classifier: Intended Audience :: End Users/Desktop
Classifier: Topic :: Office/Business :: Scheduling
Classifier: Topic :: Utilities
Classifier: License :: OSI Approved :: MIT License
Classifier: Programming Language :: Python :: 3
Classifier: Environment :: Console
Requires-Python: >=3
Requires-Dist: docopt (>=0.6.2)
